crosstream/__init__.py
crosstream/api.py
crosstream/hash_join.py
crosstream/readers.py
crosstream-3.0.0.dist-info/LICENSE
crosstream-3.0.0.dist-info/METADATA
crosstream-3.0.0.dist-info/WHEEL
crosstream-3.0.0.dist-info/top_level.txt
crosstream-3.0.0.dist-info/RECORD
