Metadata-Version: 2.1
Name: crosstream
Version: 3.0.0
Summary: A package for streaming cross-server dataset joins in memory
Home-page: https://github.com/bertwagner/crosstream
Author: Bert Wagner
Requires-Python: >=3.6
License-File: LICENSE
Requires-Dist: pyodbc
Provides-Extra: test
Requires-Dist: pytest ; extra == 'test'
Requires-Dist: pytest-cov ; extra == 'test'
